hyperfast/__init__.py
hyperfast/_version.py
hyperfast/config.py
hyperfast/hyperfast.py
hyperfast/model.py
hyperfast/utils.py
hyperfast-1.0.6.dist-info/LICENSE
hyperfast-1.0.6.dist-info/METADATA
hyperfast-1.0.6.dist-info/WHEEL
hyperfast-1.0.6.dist-info/top_level.txt
hyperfast-1.0.6.dist-info/RECORD
