Metadata-Version: 2.2
Name: hyperfast
Version: 1.0.6
Summary: HyperFast: Instant Classification for Tabular Data
Home-page: https://github.com/AI-sandbox/hyperfast
Author: David Bonet
Author-email: davidbonetsole@gmail.com
License: CC BY-NC 4.0
Classifier: Programming Language :: Python :: 3.9
Classifier: Programming Language :: Python :: 3.10
Classifier: Programming Language :: Python :: 3.11
Classifier: Operating System :: OS Independent
Requires-Python: >=3.9
License-File: LICENSE
Requires-Dist: numpy>=1.26.2
Requires-Dist: pandas>=2.1.3
Requires-Dist: scikit-learn<1.7,>=1.3.2
Requires-Dist: torch>=1.10.2
Requires-Dist: requests>=2.31.0
